Metadata-Version: 1.1
Name: simon-game
Version: 0.0.2
Summary: command line simon game
Home-page: https://github.com/darrylbalderas/simon-game
Author: Darryl Balderas
Author-email: drrylbalderas@gmail.com
License: MIT
Platform: UNKNOWN
Classifier: Programming Language :: Python
Classifier: Programming Language :: Python :: 2.7
Classifier: Programming Language :: Python :: 3.4
